{
  "gameContext": {
    "windowWidth": 800,
    "windowHeight": 800,
    "paddingX": 8,
    "paddingY": 8,
    "scaled": 0.8,
    "paddle": {
      "dx": 0.0,
      "dy": 0.0,
      "speed": 5.0,
      "scaledSpeed": 10.0,
      "isSpeedScaled": false,
      "texturePath": "/textures/paddle.png",
      "textureX": 0,
      "textureY": 0,
      "textureWidth": 96,
      "textureHeight": 24,
      "indexFrame": 0,
      "numberOfFrames": 1,
      "x": 200.0,
      "y": 640.0,
      "width": 160.0,
      "height": 40.0,
      "relativeSize": 0.2,
      "relativeX": 0.25,
      "relativeY": 0.8,
      "originalWidth": 160.0,
      "originalHeight": 40.0,
      "isSizeScaled": false
    },
    "ball": {
      "isMoving": true,
      "isBallLost": false,
      "paddle": {
        "dx": 0.0,
        "dy": 0.0,
        "speed": 5.0,
        "scaledSpeed": 10.0,
        "isSpeedScaled": false,
        "texturePath": "/textures/paddle.png",
        "textureX": 0,
        "textureY": 0,
        "textureWidth": 96,
        "textureHeight": 24,
        "indexFrame": 0,
        "numberOfFrames": 1,
        "x": 200.0,
        "y": 640.0,
        "width": 160.0,
        "height": 40.0,
        "relativeSize": 0.2,
        "relativeX": 0.25,
        "relativeY": 0.8,
        "originalWidth": 160.0,
        "originalHeight": 40.0,
        "isSizeScaled": false
      },
      "dx": 0.5036823,
      "dy": -1.0903581,
      "speed": 5.0,
      "scaledSpeed": 2.5,
      "isSpeedScaled": false,
      "texturePath": "/textures/ball.png",
      "textureX": 0,
      "textureY": 0,
      "textureWidth": 24,
      "textureHeight": 24,
      "indexFrame": 0,
      "numberOfFrames": 4,
      "x": 182.33324,
      "y": 161.67665,
      "width": 40.0,
      "height": 40.0,
      "relativeSize": 0.05,
      "relativeX": 0.22791654,
      "relativeY": 0.2020958,
      "originalWidth": 40.0,
      "originalHeight": 40.0,
      "isSizeScaled": false
    },
    "lifeCounter": {
      "lives": 7,
      "totalLives": 7,
      "texturePath": "/textures/hearts.png",
      "textureX": 0,
      "textureY": 0,
      "textureWidth": 11,
      "textureHeight": 10,
      "indexFrame": 0,
      "numberOfFrames": 7,
      "x": 712.0,
      "y": 719.2727,
      "width": 80.0,
      "height": 72.72727,
      "relativeSize": 0.1,
      "relativeX": 0.89,
      "relativeY": 0.8990909,
      "originalWidth": 80.0,
      "originalHeight": 72.72727,
      "isSizeScaled": false
    }
  },
  "brickManager": {
    "bricks": [
      [
        {
          "destroyed": false,
          "hit": false,
          "texturePath": "/textures/brick.png",
          "textureX": 0,
          "textureY": 160,
          "textureWidth": 32,
          "textureHeight": 16,
          "indexFrame": 0,
          "numberOfFrames": 1,
          "x": 0.0,
          "y": 0.0,
          "width": 80.0,
          "height": 40.0,
          "relativeSize": 0.1,
          "relativeX": 0.0,
          "relativeY": 0.0,
          "originalWidth": 80.0,
          "originalHeight": 40.0,
          "isSizeScaled": false,
          "className": "object.brick.PowerUpBrick"
        },
        {
          "destroyed": false,
          "hit": false,
          "texturePath": "/textures/brick.png",
          "textureX": 0,
          "textureY": 160,
          "textureWidth": 32,
          "textureHeight": 16,
          "indexFrame": 0,
          "numberOfFrames": 1,
          "x": 80.0,
          "y": 0.0,
          "width": 80.0,
          "height": 40.0,
          "relativeSize": 0.1,
          "relativeX": 0.1,
          "relativeY": 0.0,
          "originalWidth": 80.0,
          "originalHeight": 40.0,
          "isSizeScaled": false,
          "className": "object.brick.PowerUpBrick"
        },
        {
          "destroyed": false,
          "hit": false,
          "texturePath": "/textures/brick.png",
          "textureX": 0,
          "textureY": 160,
          "textureWidth": 32,
          "textureHeight": 16,
          "indexFrame": 0,
          "numberOfFrames": 1,
          "x": 160.0,
          "y": 0.0,
          "width": 80.0,
          "height": 40.0,
          "relativeSize": 0.1,
          "relativeX": 0.2,
          "relativeY": 0.0,
          "originalWidth": 80.0,
          "originalHeight": 40.0,
          "isSizeScaled": false,
          "className": "object.brick.PowerUpBrick"
        },
        {
          "destroyed": false,
          "hit": false,
          "texturePath": "/textures/brick.png",
          "textureX": 0,
          "textureY": 176,
          "textureWidth": 32,
          "textureHeight": 16,
          "indexFrame": 0,
          "numberOfFrames": 1,
          "x": 240.00002,
          "y": 0.0,
          "width": 80.0,
          "height": 40.0,
          "relativeSize": 0.1,
          "relativeX": 0.3,
          "relativeY": 0.0,
          "originalWidth": 80.0,
          "originalHeight": 40.0,
          "isSizeScaled": false,
          "className": "object.brick.PowerUpBrick"
        },
        {
          "destroyed": false,
          "hit": false,
          "texturePath": "/textures/brick.png",
          "textureX": 0,
          "textureY": 176,
          "textureWidth": 32,
          "textureHeight": 16,
          "indexFrame": 0,
          "numberOfFrames": 1,
          "x": 320.0,
          "y": 0.0,
          "width": 80.0,
          "height": 40.0,
          "relativeSize": 0.1,
          "relativeX": 0.4,
          "relativeY": 0.0,
          "originalWidth": 80.0,
          "originalHeight": 40.0,
          "isSizeScaled": false,
          "className": "object.brick.PowerUpBrick"
        },
        {
          "destroyed": false,
          "hit": false,
          "texturePath": "/textures/brick.png",
          "textureX": 0,
          "textureY": 176,
          "textureWidth": 32,
          "textureHeight": 16,
          "indexFrame": 0,
          "numberOfFrames": 1,
          "x": 400.0,
          "y": 0.0,
          "width": 80.0,
          "height": 40.0,
          "relativeSize": 0.1,
          "relativeX": 0.5,
          "relativeY": 0.0,
          "originalWidth": 80.0,
          "originalHeight": 40.0,
          "isSizeScaled": false,
          "className": "object.brick.PowerUpBrick"
        },
        {
          "destroyed": false,
          "hit": false,
          "texturePath": "/textures/brick.png",
          "textureX": 0,
          "textureY": 176,
          "textureWidth": 32,
          "textureHeight": 16,
          "indexFrame": 0,
          "numberOfFrames": 1,
          "x": 480.00003,
          "y": 0.0,
          "width": 80.0,
          "height": 40.0,
          "relativeSize": 0.1,
          "relativeX": 0.6,
          "relativeY": 0.0,
          "originalWidth": 80.0,
          "originalHeight": 40.0,
          "isSizeScaled": false,
          "className": "object.brick.PowerUpBrick"
        },
        {
          "destroyed": false,
          "hit": false,
          "texturePath": "/textures/brick.png",
          "textureX": 0,
          "textureY": 192,
          "textureWidth": 32,
          "textureHeight": 16,
          "indexFrame": 0,
          "numberOfFrames": 1,
          "x": 560.0,
          "y": 0.0,
          "width": 80.0,
          "height": 40.0,
          "relativeSize": 0.1,
          "relativeX": 0.7,
          "relativeY": 0.0,
          "originalWidth": 80.0,
          "originalHeight": 40.0,
          "isSizeScaled": false,
          "className": "object.brick.PowerUpBrick"
        },
        {
          "destroyed": false,
          "hit": false,
          "texturePath": "/textures/brick.png",
          "textureX": 0,
          "textureY": 192,
          "textureWidth": 32,
          "textureHeight": 16,
          "indexFrame": 0,
          "numberOfFrames": 1,
          "x": 640.0,
          "y": 0.0,
          "width": 80.0,
          "height": 40.0,
          "relativeSize": 0.1,
          "relativeX": 0.8,
          "relativeY": 0.0,
          "originalWidth": 80.0,
          "originalHeight": 40.0,
          "isSizeScaled": false,
          "className": "object.brick.PowerUpBrick"
        },
        {
          "destroyed": false,
          "hit": false,
          "texturePath": "/textures/brick.png",
          "textureX": 0,
          "textureY": 192,
          "textureWidth": 32,
          "textureHeight": 16,
          "indexFrame": 0,
          "numberOfFrames": 1,
          "x": 720.0,
          "y": 0.0,
          "width": 80.0,
          "height": 40.0,
          "relativeSize": 0.1,
          "relativeX": 0.9,
          "relativeY": 0.0,
          "originalWidth": 80.0,
          "originalHeight": 40.0,
          "isSizeScaled": false,
          "className": "object.brick.PowerUpBrick"
        }
      ],
      [
        {
          "destroyed": false,
          "hit": false,
          "texturePath": "/textures/brick.png",
          "textureX": 0,
          "textureY": 160,
          "textureWidth": 32,
          "textureHeight": 16,
          "indexFrame": 0,
          "numberOfFrames": 1,
          "x": 0.0,
          "y": 40.0,
          "width": 80.0,
          "height": 40.0,
          "relativeSize": 0.1,
          "relativeX": 0.0,
          "relativeY": 0.05,
          "originalWidth": 80.0,
          "originalHeight": 40.0,
          "isSizeScaled": false,
          "className": "object.brick.PowerUpBrick"
        },
        {
          "destroyed": false,
          "hit": false,
          "texturePath": "/textures/brick.png",
          "textureX": 0,
          "textureY": 160,
          "textureWidth": 32,
          "textureHeight": 16,
          "indexFrame": 0,
          "numberOfFrames": 1,
          "x": 80.0,
          "y": 40.0,
          "width": 80.0,
          "height": 40.0,
          "relativeSize": 0.1,
          "relativeX": 0.1,
          "relativeY": 0.05,
          "originalWidth": 80.0,
          "originalHeight": 40.0,
          "isSizeScaled": false,
          "className": "object.brick.PowerUpBrick"
        },
        {
          "destroyed": false,
          "hit": false,
          "texturePath": "/textures/brick.png",
          "textureX": 0,
          "textureY": 160,
          "textureWidth": 32,
          "textureHeight": 16,
          "indexFrame": 0,
          "numberOfFrames": 1,
          "x": 160.0,
          "y": 40.0,
          "width": 80.0,
          "height": 40.0,
          "relativeSize": 0.1,
          "relativeX": 0.2,
          "relativeY": 0.05,
          "originalWidth": 80.0,
          "originalHeight": 40.0,
          "isSizeScaled": false,
          "className": "object.brick.PowerUpBrick"
        },
        {
          "destroyed": false,
          "hit": false,
          "texturePath": "/textures/brick.png",
          "textureX": 0,
          "textureY": 160,
          "textureWidth": 32,
          "textureHeight": 16,
          "indexFrame": 0,
          "numberOfFrames": 1,
          "x": 240.00002,
          "y": 40.0,
          "width": 80.0,
          "height": 40.0,
          "relativeSize": 0.1,
          "relativeX": 0.3,
          "relativeY": 0.05,
          "originalWidth": 80.0,
          "originalHeight": 40.0,
          "isSizeScaled": false,
          "className": "object.brick.PowerUpBrick"
        },
        {
          "destroyed": false,
          "hit": false,
          "texturePath": "/textures/brick.png",
          "textureX": 0,
          "textureY": 176,
          "textureWidth": 32,
          "textureHeight": 16,
          "indexFrame": 0,
          "numberOfFrames": 1,
          "x": 320.0,
          "y": 40.0,
          "width": 80.0,
          "height": 40.0,
          "relativeSize": 0.1,
          "relativeX": 0.4,
          "relativeY": 0.05,
          "originalWidth": 80.0,
          "originalHeight": 40.0,
          "isSizeScaled": false,
          "className": "object.brick.PowerUpBrick"
        },
        {
          "destroyed": false,
          "hit": false,
          "texturePath": "/textures/brick.png",
          "textureX": 0,
          "textureY": 240,
          "textureWidth": 32,
          "textureHeight": 16,
          "indexFrame": 0,
          "numberOfFrames": 1,
          "x": 400.0,
          "y": 40.0,
          "width": 80.0,
          "height": 40.0,
          "relativeSize": 0.1,
          "relativeX": 0.5,
          "relativeY": 0.05,
          "originalWidth": 80.0,
          "originalHeight": 40.0,
          "isSizeScaled": false,
          "className": "object.brick.PowerUpBrick"
        },
        {
          "destroyed": false,
          "hit": false,
          "texturePath": "/textures/brick.png",
          "textureX": 0,
          "textureY": 224,
          "textureWidth": 32,
          "textureHeight": 16,
          "indexFrame": 0,
          "numberOfFrames": 1,
          "x": 480.00003,
          "y": 40.0,
          "width": 80.0,
          "height": 40.0,
          "relativeSize": 0.1,
          "relativeX": 0.6,
          "relativeY": 0.05,
          "originalWidth": 80.0,
          "originalHeight": 40.0,
          "isSizeScaled": false,
          "className": "object.brick.PowerUpBrick"
        },
        {
          "destroyed": false,
          "hit": false,
          "texturePath": "/textures/brick.png",
          "textureX": 0,
          "textureY": 192,
          "textureWidth": 32,
          "textureHeight": 16,
          "indexFrame": 0,
          "numberOfFrames": 1,
          "x": 560.0,
          "y": 40.0,
          "width": 80.0,
          "height": 40.0,
          "relativeSize": 0.1,
          "relativeX": 0.7,
          "relativeY": 0.05,
          "originalWidth": 80.0,
          "originalHeight": 40.0,
          "isSizeScaled": false,
          "className": "object.brick.PowerUpBrick"
        },
        {
          "destroyed": false,
          "hit": false,
          "texturePath": "/textures/brick.png",
          "textureX": 0,
          "textureY": 192,
          "textureWidth": 32,
          "textureHeight": 16,
          "indexFrame": 0,
          "numberOfFrames": 1,
          "x": 640.0,
          "y": 40.0,
          "width": 80.0,
          "height": 40.0,
          "relativeSize": 0.1,
          "relativeX": 0.8,
          "relativeY": 0.05,
          "originalWidth": 80.0,
          "originalHeight": 40.0,
          "isSizeScaled": false,
          "className": "object.brick.PowerUpBrick"
        },
        {
          "destroyed": false,
          "hit": false,
          "texturePath": "/textures/brick.png",
          "textureX": 0,
          "textureY": 224,
          "textureWidth": 32,
          "textureHeight": 16,
          "indexFrame": 0,
          "numberOfFrames": 1,
          "x": 720.0,
          "y": 40.0,
          "width": 80.0,
          "height": 40.0,
          "relativeSize": 0.1,
          "relativeX": 0.9,
          "relativeY": 0.05,
          "originalWidth": 80.0,
          "originalHeight": 40.0,
          "isSizeScaled": false,
          "className": "object.brick.PowerUpBrick"
        }
      ],
      [
        {
          "destroyed": false,
          "hit": false,
          "texturePath": "/textures/brick.png",
          "textureX": 0,
          "textureY": 240,
          "textureWidth": 32,
          "textureHeight": 16,
          "indexFrame": 0,
          "numberOfFrames": 1,
          "x": 0.0,
          "y": 80.0,
          "width": 80.0,
          "height": 40.0,
          "relativeSize": 0.1,
          "relativeX": 0.0,
          "relativeY": 0.1,
          "originalWidth": 80.0,
          "originalHeight": 40.0,
          "isSizeScaled": false,
          "className": "object.brick.PowerUpBrick"
        },
        {
          "destroyed": false,
          "hit": false,
          "texturePath": "/textures/brick.png",
          "textureX": 0,
          "textureY": 240,
          "textureWidth": 32,
          "textureHeight": 16,
          "indexFrame": 0,
          "numberOfFrames": 1,
          "x": 80.0,
          "y": 80.0,
          "width": 80.0,
          "height": 40.0,
          "relativeSize": 0.1,
          "relativeX": 0.1,
          "relativeY": 0.1,
          "originalWidth": 80.0,
          "originalHeight": 40.0,
          "isSizeScaled": false,
          "className": "object.brick.PowerUpBrick"
        },
        {
          "destroyed": false,
          "hit": false,
          "texturePath": "/textures/brick.png",
          "textureX": 0,
          "textureY": 240,
          "textureWidth": 32,
          "textureHeight": 16,
          "indexFrame": 0,
          "numberOfFrames": 1,
          "x": 160.0,
          "y": 80.0,
          "width": 80.0,
          "height": 40.0,
          "relativeSize": 0.1,
          "relativeX": 0.2,
          "relativeY": 0.1,
          "originalWidth": 80.0,
          "originalHeight": 40.0,
          "isSizeScaled": false,
          "className": "object.brick.PowerUpBrick"
        },
        null,
        {
          "destroyed": false,
          "hit": false,
          "texturePath": "/textures/brick.png",
          "textureX": 0,
          "textureY": 240,
          "textureWidth": 32,
          "textureHeight": 16,
          "indexFrame": 0,
          "numberOfFrames": 1,
          "x": 320.0,
          "y": 80.0,
          "width": 80.0,
          "height": 40.0,
          "relativeSize": 0.1,
          "relativeX": 0.4,
          "relativeY": 0.1,
          "originalWidth": 80.0,
          "originalHeight": 40.0,
          "isSizeScaled": false,
          "className": "object.brick.PowerUpBrick"
        },
        {
          "destroyed": false,
          "hit": false,
          "texturePath": "/textures/brick.png",
          "textureX": 0,
          "textureY": 240,
          "textureWidth": 32,
          "textureHeight": 16,
          "indexFrame": 0,
          "numberOfFrames": 1,
          "x": 400.0,
          "y": 80.0,
          "width": 80.0,
          "height": 40.0,
          "relativeSize": 0.1,
          "relativeX": 0.5,
          "relativeY": 0.1,
          "originalWidth": 80.0,
          "originalHeight": 40.0,
          "isSizeScaled": false,
          "className": "object.brick.PowerUpBrick"
        },
        {
          "destroyed": false,
          "hit": false,
          "texturePath": "/textures/brick.png",
          "textureX": 0,
          "textureY": 224,
          "textureWidth": 32,
          "textureHeight": 16,
          "indexFrame": 0,
          "numberOfFrames": 1,
          "x": 480.00003,
          "y": 80.0,
          "width": 80.0,
          "height": 40.0,
          "relativeSize": 0.1,
          "relativeX": 0.6,
          "relativeY": 0.1,
          "originalWidth": 80.0,
          "originalHeight": 40.0,
          "isSizeScaled": false,
          "className": "object.brick.PowerUpBrick"
        },
        null,
        null,
        {
          "destroyed": false,
          "hit": false,
          "texturePath": "/textures/brick.png",
          "textureX": 0,
          "textureY": 224,
          "textureWidth": 32,
          "textureHeight": 16,
          "indexFrame": 0,
          "numberOfFrames": 1,
          "x": 720.0,
          "y": 80.0,
          "width": 80.0,
          "height": 40.0,
          "relativeSize": 0.1,
          "relativeX": 0.9,
          "relativeY": 0.1,
          "originalWidth": 80.0,
          "originalHeight": 40.0,
          "isSizeScaled": false,
          "className": "object.brick.PowerUpBrick"
        }
      ],
      [
        null,
        null,
        null,
        null,
        null,
        {
          "destroyed": false,
          "hit": false,
          "texturePath": "/textures/brick.png",
          "textureX": 0,
          "textureY": 192,
          "textureWidth": 32,
          "textureHeight": 16,
          "indexFrame": 0,
          "numberOfFrames": 1,
          "x": 400.0,
          "y": 120.00001,
          "width": 80.0,
          "height": 40.0,
          "relativeSize": 0.1,
          "relativeX": 0.5,
          "relativeY": 0.15,
          "originalWidth": 80.0,
          "originalHeight": 40.0,
          "isSizeScaled": false,
          "className": "object.brick.PowerUpBrick"
        },
        {
          "destroyed": false,
          "hit": false,
          "texturePath": "/textures/brick.png",
          "textureX": 0,
          "textureY": 256,
          "textureWidth": 32,
          "textureHeight": 16,
          "indexFrame": 0,
          "numberOfFrames": 1,
          "x": 480.00003,
          "y": 120.00001,
          "width": 80.0,
          "height": 40.0,
          "relativeSize": 0.1,
          "relativeX": 0.6,
          "relativeY": 0.15,
          "originalWidth": 80.0,
          "originalHeight": 40.0,
          "isSizeScaled": false,
          "className": "object.brick.PowerUpBrick"
        },
        null,
        null,
        null
      ],
      [
        null,
        null,
        null,
        null,
        null,
        null,
        null,
        null,
        null,
        null
      ],
      [
        null,
        null,
        null,
        null,
        null,
        null,
        null,
        null,
        null,
        null
      ],
      [
        null,
        null,
        null,
        null,
        null,
        null,
        null,
        null,
        null,
        null
      ],
      [
        null,
        null,
        null,
        null,
        null,
        null,
        null,
        null,
        null,
        null
      ],
      [
        null,
        null,
        null,
        null,
        null,
        null,
        null,
        null,
        null,
        null
      ],
      [
        null,
        null,
        null,
        null,
        null,
        null,
        null,
        null,
        null,
        null
      ],
      [
        null,
        null,
        null,
        null,
        null,
        null,
        null,
        null,
        null,
        null
      ],
      [
        null,
        null,
        null,
        null,
        null,
        null,
        null,
        null,
        null,
        null
      ],
      [
        null,
        null,
        null,
        null,
        null,
        null,
        null,
        null,
        null,
        null
      ],
      [
        null,
        null,
        null,
        null,
        null,
        null,
        null,
        null,
        null,
        null
      ],
      [
        null,
        null,
        null,
        null,
        null,
        null,
        null,
        null,
        null,
        null
      ],
      [
        null,
        null,
        null,
        null,
        null,
        null,
        null,
        null,
        null,
        null
      ],
      [
        null,
        null,
        null,
        null,
        null,
        null,
        null,
        null,
        null,
        null
      ],
      [
        null,
        null,
        null,
        null,
        null,
        null,
        null,
        null,
        null,
        null
      ],
      [
        null,
        null,
        null,
        null,
        null,
        null,
        null,
        null,
        null,
        null
      ],
      [
        null,
        null,
        null,
        null,
        null,
        null,
        null,
        null,
        null,
        null
      ]
    ],
    "brickWidth": 80,
    "brickHeight": 40,
    "brickCountX": 10,
    "brickCountY": 20,
    "brickRegistry": {},
    "normalBrickTextureSet": [],
    "strongBrickTextureSet": [],
    "powerUpBrickTextureSet": [],
    "framePerRow": 11,
    "destroyedBricksCount": 57,
    "totalBricksCount": 86,
    "isIncremented": false
  },
  "powerUpManager": {
    "powerUpsRegistry": {
      "SLOW_BALL": {
        "slowMultiplier": 0.5,
        "isFalling": false,
        "isRemoved": false,
        "durationMs": 5000,
        "dx": 0.0,
        "dy": 0.0,
        "speed": 3.0,
        "scaledSpeed": 0.0,
        "isSpeedScaled": false,
        "texturePath": "/textures/slow_ball.png",
        "textureX": 0,
        "textureY": 0,
        "textureWidth": 14,
        "textureHeight": 20,
        "indexFrame": 0,
        "numberOfFrames": 1,
        "x": 0.0,
        "y": 0.0,
        "width": 0.0,
        "height": 0.0,
        "relativeSize": 0.05,
        "relativeX": 0.0,
        "relativeY": 0.0,
        "originalWidth": 0.0,
        "originalHeight": 0.0,
        "isSizeScaled": false,
        "className": "object.movable.powerup.SlowBallPowerUp"
      },
      "EXPAND_PADDLE": {
        "widthMultiplier": 2.0,
        "isFalling": false,
        "isRemoved": false,
        "durationMs": 5000,
        "dx": 0.0,
        "dy": 0.0,
        "speed": 3.0,
        "scaledSpeed": 0.0,
        "isSpeedScaled": false,
        "texturePath": "/textures/expand_paddle.png",
        "textureX": 0,
        "textureY": 0,
        "textureWidth": 25,
        "textureHeight": 6,
        "indexFrame": 0,
        "numberOfFrames": 1,
        "x": 0.0,
        "y": 0.0,
        "width": 0.0,
        "height": 0.0,
        "relativeSize": 0.1,
        "relativeX": 0.0,
        "relativeY": 0.0,
        "originalWidth": 0.0,
        "originalHeight": 0.0,
        "isSizeScaled": false,
        "className": "object.movable.powerup.ExpandPaddlePowerUp"
      },
      "SPEEDUP_PADDLE": {
        "speedUpMultiplier": 2.0,
        "isFalling": false,
        "isRemoved": false,
        "durationMs": 5000,
        "dx": 0.0,
        "dy": 0.0,
        "speed": 3.0,
        "scaledSpeed": 0.0,
        "isSpeedScaled": false,
        "texturePath": "/textures/speedup_paddle.png",
        "textureX": 0,
        "textureY": 0,
        "textureWidth": 22,
        "textureHeight": 7,
        "indexFrame": 0,
        "numberOfFrames": 1,
        "x": 0.0,
        "y": 0.0,
        "width": 0.0,
        "height": 0.0,
        "relativeSize": 0.1,
        "relativeX": 0.0,
        "relativeY": 0.0,
        "originalWidth": 0.0,
        "originalHeight": 0.0,
        "isSizeScaled": false,
        "className": "object.movable.powerup.SpeedUpPaddlePowerUp"
      }
    },
    "activePowerUps": {
      "EXPAND_PADDLE": {
        "widthMultiplier": 2.0,
        "isFalling": false,
        "isRemoved": true,
        "durationMs": 5000,
        "powerUpType": "EXPAND_PADDLE",
        "dx": 0.0,
        "dy": 1.0,
        "speed": 3.0,
        "scaledSpeed": 0.0,
        "isSpeedScaled": false,
        "texturePath": "/textures/expand_paddle.png",
        "textureX": 0,
        "textureY": 0,
        "textureWidth": 25,
        "textureHeight": 6,
        "indexFrame": 0,
        "numberOfFrames": 1,
        "x": 240.00002,
        "y": 622.40015,
        "width": 80.0,
        "height": 19.2,
        "relativeSize": 0.1,
        "relativeX": 0.0,
        "relativeY": 0.0,
        "originalWidth": 0.0,
        "originalHeight": 0.0,
        "isSizeScaled": false,
        "className": "object.movable.powerup.ExpandPaddlePowerUp"
      },
      "SLOW_BALL": {
        "slowMultiplier": 0.5,
        "isFalling": false,
        "isRemoved": true,
        "durationMs": 5000,
        "powerUpType": "SLOW_BALL",
        "dx": 0.0,
        "dy": 1.0,
        "speed": 3.0,
        "scaledSpeed": 0.0,
        "isSpeedScaled": false,
        "texturePath": "/textures/slow_ball.png",
        "textureX": 0,
        "textureY": 0,
        "textureWidth": 14,
        "textureHeight": 20,
        "indexFrame": 0,
        "numberOfFrames": 1,
        "x": 340.0,
        "y": 583.19977,
        "width": 40.0,
        "height": 57.142857,
        "relativeSize": 0.05,
        "relativeX": 0.0,
        "relativeY": 0.0,
        "originalWidth": 0.0,
        "originalHeight": 0.0,
        "isSizeScaled": false,
        "className": "object.movable.powerup.SlowBallPowerUp"
      }
    },
    "fallingPowerUps": [],
    "lock": {},
    "startTimes": {
      "EXPAND_PADDLE": 1762097167945,
      "SLOW_BALL": 1762097167460
    },
    "remainingTimes": {
      "EXPAND_PADDLE": 4828,
      "SLOW_BALL": 4343
    },
    "paused": true
  },
  "levelId": "PLAY_LEVEL2",
  "scoreText": {
    "content": "Score: ",
    "colorData": {
      "r": 255,
      "g": 255,
      "b": 255,
      "a": 255
    },
    "fontData": {
      "fontPath": "/fonts/PixelOperator.ttf",
      "style": "BOLD",
      "size": 24
    },
    "x": 8.0,
    "y": 768.0,
    "width": 118.0,
    "height": 24.0,
    "relativeSize": 0.05,
    "relativeX": 0.01,
    "relativeY": 0.96,
    "originalWidth": 0.0,
    "originalHeight": 0.0,
    "isSizeScaled": false
  },
  "numScoreText": {
    "content": "57",
    "colorData": {
      "r": 255,
      "g": 255,
      "b": 0,
      "a": 255
    },
    "fontData": {
      "fontPath": "/fonts/PixelOperator.ttf",
      "style": "BOLD",
      "size": 24
    },
    "x": 134.66667,
    "y": 768.0,
    "width": 38.0,
    "height": 24.0,
    "relativeSize": 0.05,
    "relativeX": 0.16833334,
    "relativeY": 0.96,
    "originalWidth": 0.0,
    "originalHeight": 0.0,
    "isSizeScaled": false
  },
  "pauseButton": {
    "texturePath": "/textures/buttons.png",
    "textureX": 80,
    "textureY": 0,
    "textureWidth": 16,
    "textureHeight": 16,
    "indexFrame": 0,
    "numberOfFrames": 1,
    "x": 380.0,
    "y": 752.0,
    "width": 40.0,
    "height": 40.0,
    "relativeSize": 0.05,
    "relativeX": 0.475,
    "relativeY": 0.94,
    "originalWidth": 40.0,
    "originalHeight": 40.0,
    "isSizeScaled": false
  },
  "numTimeText": {
    "content": "00:02:43",
    "colorData": {
      "r": 255,
      "g": 255,
      "b": 0,
      "a": 255
    },
    "fontData": {
      "fontPath": "/fonts/PixelOperator.ttf",
      "style": "BOLD",
      "size": 24
    },
    "x": 508.0,
    "y": 768.0,
    "width": 141.0,
    "height": 24.0,
    "relativeSize": 0.05,
    "relativeX": 0.635,
    "relativeY": 0.96,
    "originalWidth": 0.0,
    "originalHeight": 0.0,
    "isSizeScaled": false
  },
  "background": {
    "texturePath": "/textures/background_level2.png",
    "textureX": 0,
    "textureY": 0,
    "textureWidth": 1000,
    "textureHeight": 1000,
    "indexFrame": 0,
    "numberOfFrames": 1,
    "x": 0.0,
    "y": 0.0,
    "width": 800.0,
    "height": 800.0,
    "relativeSize": 1.0,
    "relativeX": 0.0,
    "relativeY": 0.0,
    "originalWidth": 800.0,
    "originalHeight": 800.0,
    "isSizeScaled": false
  },
  "levelInitPath": "assets/json/levels/Level2.json",
  "levelSavePath": "assets/json/saveLevels/Level2.json",
  "startTime": 1762097117141,
  "pauseStartTime": 1762097168117,
  "pauseTime": 0,
  "endTime": 1762097168117,
  "totalTimePlayed": 163966,
  "isPaused": true,
  "exited": false
}